<x:xmpmeta tsc:version="2.0.1" xmlns:x="adobe:ns:meta/" xmlns:tsc="http://www.techsmith.com/xmp/tsc/">
   <rdf:RDF xmlns:rdf="http://www.w3.org/1999/02/22-rdf-syntax-ns#" xmlns:xmp="http://ns.adobe.com/xap/1.0/" xmlns:xmpDM="http://ns.adobe.com/xmp/1.0/DynamicMedia/" xmlns:xmpG="http://ns.adobe.com/xap/1.0/g/" xmlns:xmpMM="http://ns.adobe.com/xap/1.0/mm/" xmlns:tscDM="http://www.techsmith.com/xmp/tscDM/" xmlns:tscIQ="http://www.techsmith.com/xmp/tscIQ/" xmlns:tscHS="http://www.techsmith.com/xmp/tscHS/" xmlns:stDim="http://ns.adobe.com/xap/1.0/sType/Dimensions#" xmlns:stFnt="http://ns.adobe.com/xap/1.0/sType/Font#" xmlns:exif="http://ns.adobe.com/exif/1.0" xmlns:dc="http://purl.org/dc/elements/1.1/">
      <rdf:Description dc:creator="Mohammad Bin Saleem" dc:date="2018-08-26 11:54:03 PM" dc:source="Camtasia,18.0.1,enu" dc:title="OriginalDMCQuizV3" tscDM:firstFrame="OriginalDMCQuizV3_First_Frame.png" tscDM:iPodExplicit="Clean" tscDM:originId="584436AA-B0A2-49C8-A7C2-057DB52E8A64" tscDM:project="Untitled Project">
         <xmpDM:duration xmpDM:scale="1/1000" xmpDM:value="50566"/>
         <xmpDM:videoFrameSize stDim:unit="pixel" stDim:h="720" stDim:w="1280"/>
         <tsc:langName>
            <rdf:Bag>
               <rdf:li xml:lang="en-US">English</rdf:li></rdf:Bag>
         </tsc:langName>
         <xmpDM:Tracks>
            <rdf:Bag>
               <rdf:li>
                  <rdf:Description xmpDM:trackType="Quiz" xmpDM:frameRate="f1000" xmpDM:trackName="Quiz" tscIQ:quizGuid="1DEE3AA5-BFA7-4FF0-9DBE-E0137DE5CB25" tscIQ:authoredEmail="a0mZva/3wgOEH1hprIbbJ+VgoatOpGXoaCMk25lFtaLosJOb1EcmUxJhAE+qwIiKIrZcslamfN0P
T9G5/xEgCfPXjjoVQnsDAPlnt8N8gvzrmLb+w2JmNIRwuhc0caWKfv5Y+2aOhergE3hR1iK08icI
LF/4g5WK22/sjfdHZ7bGufeRDv4gc7Kv8GJDmB1Z25MkMQW2QyKGvl4bdCc6KazxD1ym6a2cIfQA
XTvBHpC/CqVCXxEZ1zGkVAsKfqZQQsoAQs4/8dUZVpJepLd010QS4rZ3f6MpOzxmFRF34njpoC7y
kF1Sw5Bcu1C5hADo0x1VkbSidjOqi0qYQ6VUag==" tscIQ:requireUserId="0" tscIQ:locale="en-US" tscIQ:reportMethod="API" tscIQ:allowSkipQuiz="0" tscIQ:clientId="0E45EC2A-7CCA-4294-84CE-CB0980980952" tscIQ:hideReplay="1" tscIQ:quizHash="2cb68e2c71aa4cff45ae4509e08b3299">
                     <xmpDM:markers>
                        <rdf:Seq>
                           <rdf:li><rdf:Description xmpDM:startTime="42400" tscIQ:feedback="1" tscIQ:questionSetName="OriginalDMCQUIZ_V3"><tscIQ:questions><rdf:Seq><rdf:li><rdf:Description tscIQ:type="MC" tscIQ:id="0"><tscIQ:question>Which one of these Devil Arms is available in Monster Hunter Frontier G in any form?</tscIQ:question><tscIQ:correctAnswer>8</tscIQ:correctAnswer><tscIQ:answerArray><rdf:Seq><rdf:li><rdf:Description tscIQ:orderId="0"><tscIQ:answer>Artemis</tscIQ:answer></rdf:Description></rdf:li><rdf:li><rdf:Description tscIQ:orderId="1"><tscIQ:answer>Lucifer</tscIQ:answer></rdf:Description></rdf:li><rdf:li><rdf:Description tscIQ:orderId="2"><tscIQ:answer>Agni and Rudra</tscIQ:answer></rdf:Description></rdf:li><rdf:li><rdf:Description tscIQ:orderId="3"><tscIQ:answer>Pandora</tscIQ:answer></rdf:Description></rdf:li></rdf:Seq></tscIQ:answerArray></rdf:Description></rdf:li><rdf:li><rdf:Description tscIQ:type="MC" tscIQ:id="1"><tscIQ:question>On which of these platforms was a Devil May Cry game planned but later cancelled?</tscIQ:question><tscIQ:correctAnswer>4</tscIQ:correctAnswer><tscIQ:answerArray><rdf:Seq><rdf:li><rdf:Description tscIQ:orderId="0"><tscIQ:answer>The Original Xbox</tscIQ:answer></rdf:Description></rdf:li><rdf:li><rdf:Description tscIQ:orderId="1"><tscIQ:answer>Playstation Vita</tscIQ:answer></rdf:Description></rdf:li><rdf:li><rdf:Description tscIQ:orderId="2"><tscIQ:answer>Playstation Portable</tscIQ:answer></rdf:Description></rdf:li><rdf:li><rdf:Description tscIQ:orderId="3"><tscIQ:answer>Nintendo Gamecube</tscIQ:answer></rdf:Description></rdf:li><rdf:li><rdf:Description tscIQ:orderId="4"><tscIQ:answer>Sega Dreamcast</tscIQ:answer></rdf:Description></rdf:li></rdf:Seq></tscIQ:answerArray></rdf:Description></rdf:li><rdf:li><rdf:Description tscIQ:type="MC" tscIQ:id="2"><tscIQ:question>As of Devil May Cry 3, the original prequel novel for Devil May Cry 1 is no longer canon</tscIQ:question><tscIQ:correctAnswer>1</tscIQ:correctAnswer><tscIQ:answerArray><rdf:Seq><rdf:li><rdf:Description tscIQ:orderId="0"><tscIQ:answer>True</tscIQ:answer></rdf:Description></rdf:li><rdf:li><rdf:Description tscIQ:orderId="1"><tscIQ:answer>False</tscIQ:answer></rdf:Description></rdf:li></rdf:Seq></tscIQ:answerArray></rdf:Description></rdf:li><rdf:li><rdf:Description tscIQ:type="MC" tscIQ:id="3"><tscIQ:question>In which of these games was Nero mentioned?</tscIQ:question><tscIQ:correctAnswer>2</tscIQ:correctAnswer><tscIQ:answerArray><rdf:Seq><rdf:li><rdf:Description tscIQ:orderId="0"><tscIQ:answer>Monster Hunter 4 Ultimate</tscIQ:answer></rdf:Description></rdf:li><rdf:li><rdf:Description tscIQ:orderId="1"><tscIQ:answer>Marvel vs Capcom 3: Fate of the Two Worlds</tscIQ:answer></rdf:Description></rdf:li><rdf:li><rdf:Description tscIQ:orderId="2"><tscIQ:answer>Monster Hunter 4 Ultimate</tscIQ:answer></rdf:Description></rdf:li></rdf:Seq></tscIQ:answerArray></rdf:Description></rdf:li><rdf:li><rdf:Description tscIQ:type="MC" tscIQ:id="4"><tscIQ:question>What is Nelo Angelo?</tscIQ:question><tscIQ:correctAnswer>1</tscIQ:correctAnswer><tscIQ:answerArray><rdf:Seq><rdf:li><rdf:Description tscIQ:orderId="0"><tscIQ:answer>Vergil's corrupted soul in an armor created by Mundus</tscIQ:answer></rdf:Description></rdf:li><rdf:li><rdf:Description tscIQ:orderId="1"><tscIQ:answer>Vergil in an armor</tscIQ:answer></rdf:Description></rdf:li><rdf:li><rdf:Description tscIQ:orderId="2"><tscIQ:answer>One of the prototypes created by the Order of The Sword</tscIQ:answer></rdf:Description></rdf:li><rdf:li><rdf:Description tscIQ:orderId="3"><tscIQ:answer>Just a machine controlled by Mundus</tscIQ:answer></rdf:Description></rdf:li></rdf:Seq></tscIQ:answerArray></rdf:Description></rdf:li><rdf:li><rdf:Description tscIQ:type="MC" tscIQ:id="5"><tscIQ:question>Which one Devil May Cry game is widely considered and believed to be unfinished, being rushed to completion from halfway development?</tscIQ:question><tscIQ:correctAnswer>2</tscIQ:correctAnswer><tscIQ:answerArray><rdf:Seq><rdf:li><rdf:Description tscIQ:orderId="0"><tscIQ:answer>Devil May Cry 1</tscIQ:answer></rdf:Description></rdf:li><rdf:li><rdf:Description tscIQ:orderId="1"><tscIQ:answer>Devil May Cry 4</tscIQ:answer></rdf:Description></rdf:li><rdf:li><rdf:Description tscIQ:orderId="2"><tscIQ:answer>Devil May Cry 2</tscIQ:answer></rdf:Description></rdf:li></rdf:Seq></tscIQ:answerArray></rdf:Description></rdf:li><rdf:li><rdf:Description tscIQ:type="MC" tscIQ:id="6"><tscIQ:question>Who voiced Gloria in Devil May Cry 4?</tscIQ:question><tscIQ:correctAnswer>1</tscIQ:correctAnswer><tscIQ:answerArray><rdf:Seq><rdf:li><rdf:Description tscIQ:orderId="0"><tscIQ:answer>Danielle Burgio</tscIQ:answer></rdf:Description></rdf:li><rdf:li><rdf:Description tscIQ:orderId="1"><tscIQ:answer>Stephanie Sheh</tscIQ:answer></rdf:Description></rdf:li><rdf:li><rdf:Description tscIQ:orderId="2"><tscIQ:answer>Laura Napoli</tscIQ:answer></rdf:Description></rdf:li></rdf:Seq></tscIQ:answerArray></rdf:Description></rdf:li><rdf:li><rdf:Description tscIQ:type="MC" tscIQ:id="7"><tscIQ:question>What is the fan nickname given to the red-coat-wearing Vergil clone fought in Devil May Cry 3: Special Edition when playing as Vergil?</tscIQ:question><tscIQ:correctAnswer>2</tscIQ:correctAnswer><tscIQ:answerArray><rdf:Seq><rdf:li><rdf:Description tscIQ:orderId="0"><tscIQ:answer>Gilver</tscIQ:answer></rdf:Description></rdf:li><rdf:li><rdf:Description tscIQ:orderId="1"><tscIQ:answer>Vante</tscIQ:answer></rdf:Description></rdf:li><rdf:li><rdf:Description tscIQ:orderId="2"><tscIQ:answer>Clone Wars</tscIQ:answer></rdf:Description></rdf:li><rdf:li><rdf:Description tscIQ:orderId="3"><tscIQ:answer>Revgil</tscIQ:answer></rdf:Description></rdf:li></rdf:Seq></tscIQ:answerArray></rdf:Description></rdf:li><rdf:li><rdf:Description tscIQ:type="MC" tscIQ:id="8"><tscIQ:question>Lucia, and Eva were originally intended to be included as pre-order bonus skins for Lady and Trish, respectively, on the Devil May Cry 4: Special Edition</tscIQ:question><tscIQ:correctAnswer>2</tscIQ:correctAnswer><tscIQ:answerArray><rdf:Seq><rdf:li><rdf:Description tscIQ:orderId="0"><tscIQ:answer>True</tscIQ:answer></rdf:Description></rdf:li><rdf:li><rdf:Description tscIQ:orderId="1"><tscIQ:answer>False</tscIQ:answer></rdf:Description></rdf:li></rdf:Seq></tscIQ:answerArray></rdf:Description></rdf:li><rdf:li><rdf:Description tscIQ:type="MC" tscIQ:id="9"><tscIQ:question>Which one of these is the name of an enemy in Devil May Cry?</tscIQ:question><tscIQ:correctAnswer>4</tscIQ:correctAnswer><tscIQ:answerArray><rdf:Seq><rdf:li><rdf:Description tscIQ:orderId="0"><tscIQ:answer>Bella Sisters</tscIQ:answer></rdf:Description></rdf:li><rdf:li><rdf:Description tscIQ:orderId="1"><tscIQ:answer>Colmillos</tscIQ:answer></rdf:Description></rdf:li><rdf:li><rdf:Description tscIQ:orderId="2"><tscIQ:answer>Kyklops</tscIQ:answer></rdf:Description></rdf:li><rdf:li><rdf:Description tscIQ:orderId="3"><tscIQ:answer>Hades</tscIQ:answer></rdf:Description></rdf:li><rdf:li><rdf:Description tscIQ:orderId="4"><tscIQ:answer>Scylla</tscIQ:answer></rdf:Description></rdf:li></rdf:Seq></tscIQ:answerArray></rdf:Description></rdf:li><rdf:li><rdf:Description tscIQ:type="MC" tscIQ:id="10"><tscIQ:question>Nico is the granddaughter of Nell Goldstein</tscIQ:question><tscIQ:correctAnswer>1</tscIQ:correctAnswer><tscIQ:answerArray><rdf:Seq><rdf:li><rdf:Description tscIQ:orderId="0"><tscIQ:answer>True</tscIQ:answer></rdf:Description></rdf:li><rdf:li><rdf:Description tscIQ:orderId="1"><tscIQ:answer>False</tscIQ:answer></rdf:Description></rdf:li></rdf:Seq></tscIQ:answerArray></rdf:Description></rdf:li><rdf:li><rdf:Description tscIQ:type="MC" tscIQ:id="11"><tscIQ:question>What are Sparda's guns called?</tscIQ:question><tscIQ:correctAnswer>1</tscIQ:correctAnswer><tscIQ:answerArray><rdf:Seq><rdf:li><rdf:Description tscIQ:orderId="0"><tscIQ:answer>Luce &amp; Ombra</tscIQ:answer></rdf:Description></rdf:li><rdf:li><rdf:Description tscIQ:orderId="1"><tscIQ:answer>Eva &amp; Ivory</tscIQ:answer></rdf:Description></rdf:li><rdf:li><rdf:Description tscIQ:orderId="2"><tscIQ:answer>Lucy &amp; Omega</tscIQ:answer></rdf:Description></rdf:li></rdf:Seq></tscIQ:answerArray></rdf:Description></rdf:li><rdf:li><rdf:Description tscIQ:type="MC" tscIQ:id="12"><tscIQ:question>What does Dante rename his shop at the end of the Devil May Cry 1?</tscIQ:question><tscIQ:correctAnswer>4</tscIQ:correctAnswer><tscIQ:answerArray><rdf:Seq><rdf:li><rdf:Description tscIQ:orderId="0"><tscIQ:answer>Devil May Cry</tscIQ:answer></rdf:Description></rdf:li><rdf:li><rdf:Description tscIQ:orderId="1"><tscIQ:answer>Devil Must Cry</tscIQ:answer></rdf:Description></rdf:li><rdf:li><rdf:Description tscIQ:orderId="2"><tscIQ:answer>Devil Never Cry</tscIQ:answer></rdf:Description></rdf:li><rdf:li><rdf:Description tscIQ:orderId="3"><tscIQ:answer>Devil Might Cry</tscIQ:answer></rdf:Description></rdf:li></rdf:Seq></tscIQ:answerArray></rdf:Description></rdf:li><rdf:li><rdf:Description tscIQ:type="MC" tscIQ:id="13"><tscIQ:question>What is the name of the music that plays when Trish appears in Devil May Cry 1?</tscIQ:question><tscIQ:correctAnswer>16</tscIQ:correctAnswer><tscIQ:answerArray><rdf:Seq><rdf:li><rdf:Description tscIQ:orderId="0"><tscIQ:answer>Family Ties</tscIQ:answer></rdf:Description></rdf:li><rdf:li><rdf:Description tscIQ:orderId="1"><tscIQ:answer>Mother's Revenge</tscIQ:answer></rdf:Description></rdf:li><rdf:li><rdf:Description tscIQ:orderId="2"><tscIQ:answer>Seeds of Love</tscIQ:answer></rdf:Description></rdf:li><rdf:li><rdf:Description tscIQ:orderId="3"><tscIQ:answer>The Theme of Trish</tscIQ:answer></rdf:Description></rdf:li><rdf:li><rdf:Description tscIQ:orderId="4"><tscIQ:answer>Mother's Voice</tscIQ:answer></rdf:Description></rdf:li></rdf:Seq></tscIQ:answerArray></rdf:Description></rdf:li><rdf:li><rdf:Description tscIQ:type="MC" tscIQ:id="14"><tscIQ:question>What does Lucia hear at the end of Devil May Cry 2?</tscIQ:question><tscIQ:correctAnswer>2</tscIQ:correctAnswer><tscIQ:answerArray><rdf:Seq><rdf:li><rdf:Description tscIQ:orderId="0"><tscIQ:answer>The sound of a coin flipping</tscIQ:answer></rdf:Description></rdf:li><rdf:li><rdf:Description tscIQ:orderId="1"><tscIQ:answer>The sound of a motorcycle</tscIQ:answer></rdf:Description></rdf:li><rdf:li><rdf:Description tscIQ:orderId="2"><tscIQ:answer>The sound of Dante's chuckle</tscIQ:answer></rdf:Description></rdf:li><rdf:li><rdf:Description tscIQ:orderId="3"><tscIQ:answer>Nothing, she just walks away</tscIQ:answer></rdf:Description></rdf:li></rdf:Seq></tscIQ:answerArray></rdf:Description></rdf:li><rdf:li><rdf:Description tscIQ:type="MC" tscIQ:id="15"><tscIQ:question>What does the voice actor of Dante from Devil May Cry 3, The Animated Series, Devil May Cry 4 and other media, Reuben Langdon think of DmC: Devil May Cry?</tscIQ:question><tscIQ:correctAnswer>4</tscIQ:correctAnswer><tscIQ:answerArray><rdf:Seq><rdf:li><rdf:Description tscIQ:orderId="0"><tscIQ:answer>He likes the game and the new Dante</tscIQ:answer></rdf:Description></rdf:li><rdf:li><rdf:Description tscIQ:orderId="1"><tscIQ:answer>He likes the game but is not a fan of the new Dante</tscIQ:answer></rdf:Description></rdf:li><rdf:li><rdf:Description tscIQ:orderId="2"><tscIQ:answer>He's not a fan of the game but likes the new Dante</tscIQ:answer></rdf:Description></rdf:li><rdf:li><rdf:Description tscIQ:orderId="3"><tscIQ:answer>He dislikes the game and the new Dante</tscIQ:answer></rdf:Description></rdf:li></rdf:Seq></tscIQ:answerArray></rdf:Description></rdf:li><rdf:li><rdf:Description tscIQ:type="MC" tscIQ:id="16"><tscIQ:question>What was the name of the place where Mundus lured Dante in the first Devil May Cry game?</tscIQ:question><tscIQ:correctAnswer>2</tscIQ:correctAnswer><tscIQ:answerArray><rdf:Seq><rdf:li><rdf:Description tscIQ:orderId="0"><tscIQ:answer>Mundus' Palace</tscIQ:answer></rdf:Description></rdf:li><rdf:li><rdf:Description tscIQ:orderId="1"><tscIQ:answer>Mallet Island</tscIQ:answer></rdf:Description></rdf:li><rdf:li><rdf:Description tscIQ:orderId="2"><tscIQ:answer>Island of Evil</tscIQ:answer></rdf:Description></rdf:li><rdf:li><rdf:Description tscIQ:orderId="3"><tscIQ:answer>Island of Darkness</tscIQ:answer></rdf:Description></rdf:li></rdf:Seq></tscIQ:answerArray></rdf:Description></rdf:li><rdf:li><rdf:Description tscIQ:type="MC" tscIQ:id="17"><tscIQ:question>Does Dante use his Devil Trigger in Devil May Cry: The Animated Series?</tscIQ:question><tscIQ:correctAnswer>1</tscIQ:correctAnswer><tscIQ:answerArray><rdf:Seq><rdf:li><rdf:Description tscIQ:orderId="0"><tscIQ:answer>True</tscIQ:answer></rdf:Description></rdf:li><rdf:li><rdf:Description tscIQ:orderId="1"><tscIQ:answer>False</tscIQ:answer></rdf:Description></rdf:li></rdf:Seq></tscIQ:answerArray></rdf:Description></rdf:li><rdf:li><rdf:Description tscIQ:type="FITB" tscIQ:id="18"><tscIQ:question>In what Devil May Cry game was Vergil absent in any form?</tscIQ:question><tscIQ:correctAnswer/><tscIQ:answerArray><rdf:Seq><rdf:li><rdf:Description tscIQ:orderId="0"><tscIQ:answer>DMC2</tscIQ:answer></rdf:Description></rdf:li><rdf:li><rdf:Description tscIQ:orderId="1"><tscIQ:answer>DMC 2</tscIQ:answer></rdf:Description></rdf:li><rdf:li><rdf:Description tscIQ:orderId="2"><tscIQ:answer>Devil May Cry 2</tscIQ:answer></rdf:Description></rdf:li></rdf:Seq></tscIQ:answerArray></rdf:Description></rdf:li><rdf:li><rdf:Description tscIQ:type="MC" tscIQ:id="19"><tscIQ:question>What was the first source to confirm Nero is indeed the son of Vergil?</tscIQ:question><tscIQ:correctAnswer>2</tscIQ:correctAnswer><tscIQ:answerArray><rdf:Seq><rdf:li><rdf:Description tscIQ:orderId="0"><tscIQ:answer>Devil May Cry Volume 1</tscIQ:answer></rdf:Description></rdf:li><rdf:li><rdf:Description tscIQ:orderId="1"><tscIQ:answer>Graphic Arts 3142 art book</tscIQ:answer></rdf:Description></rdf:li><rdf:li><rdf:Description tscIQ:orderId="2"><tscIQ:answer>Devil May Cry 4 - Devil's Material Collection</tscIQ:answer></rdf:Description></rdf:li></rdf:Seq></tscIQ:answerArray></rdf:Description></rdf:li><rdf:li><rdf:Description tscIQ:type="MC" tscIQ:id="20"><tscIQ:question>Did Dante call Patty 'daughter' at any point in Devil May Cry: The Animated Series?</tscIQ:question><tscIQ:correctAnswer>1</tscIQ:correctAnswer><tscIQ:answerArray><rdf:Seq><rdf:li><rdf:Description tscIQ:orderId="0"><tscIQ:answer>True</tscIQ:answer></rdf:Description></rdf:li><rdf:li><rdf:Description tscIQ:orderId="1"><tscIQ:answer>False</tscIQ:answer></rdf:Description></rdf:li></rdf:Seq></tscIQ:answerArray></rdf:Description></rdf:li><rdf:li><rdf:Description tscIQ:type="MC" tscIQ:id="21"><tscIQ:question>Between all the bosses Nero fights in Devil May Cry 4, he only kills ONE boss during the entire game.</tscIQ:question><tscIQ:correctAnswer>2</tscIQ:correctAnswer><tscIQ:answerArray><rdf:Seq><rdf:li><rdf:Description tscIQ:orderId="0"><tscIQ:answer>True</tscIQ:answer></rdf:Description></rdf:li><rdf:li><rdf:Description tscIQ:orderId="1"><tscIQ:answer>False</tscIQ:answer></rdf:Description></rdf:li></rdf:Seq></tscIQ:answerArray></rdf:Description></rdf:li><rdf:li><rdf:Description tscIQ:type="FITB" tscIQ:id="22"><tscIQ:question>What is the name of the person who finds Dante jobs in Devil May Cry: The Animated Series?</tscIQ:question><tscIQ:correctAnswer/><tscIQ:answerArray><rdf:Seq><rdf:li><rdf:Description tscIQ:orderId="0"><tscIQ:answer>Morrison</tscIQ:answer></rdf:Description></rdf:li><rdf:li><rdf:Description tscIQ:orderId="1"><tscIQ:answer>J.D. Morison</tscIQ:answer></rdf:Description></rdf:li><rdf:li><rdf:Description tscIQ:orderId="2"><tscIQ:answer>J D  Morison</tscIQ:answer></rdf:Description></rdf:li><rdf:li><rdf:Description tscIQ:orderId="3"><tscIQ:answer>Morison</tscIQ:answer></rdf:Description></rdf:li><rdf:li><rdf:Description tscIQ:orderId="4"><tscIQ:answer>Morison</tscIQ:answer></rdf:Description></rdf:li></rdf:Seq></tscIQ:answerArray></rdf:Description></rdf:li><rdf:li><rdf:Description tscIQ:type="FITB" tscIQ:id="23"><tscIQ:question>How many forms can the Pandora weapon in Devil May Cry 4 take?</tscIQ:question><tscIQ:correctAnswer/><tscIQ:answerArray><rdf:Seq><rdf:li><rdf:Description tscIQ:orderId="0"><tscIQ:answer>666</tscIQ:answer></rdf:Description></rdf:li></rdf:Seq></tscIQ:answerArray></rdf:Description></rdf:li><rdf:li><rdf:Description tscIQ:type="MC" tscIQ:id="24"><tscIQ:question>Which one of these games did Dante make an appearance in?</tscIQ:question><tscIQ:correctAnswer>4</tscIQ:correctAnswer><tscIQ:answerArray><rdf:Seq><rdf:li><rdf:Description tscIQ:orderId="0"><tscIQ:answer>Soulcalibur III</tscIQ:answer></rdf:Description></rdf:li><rdf:li><rdf:Description tscIQ:orderId="1"><tscIQ:answer>Street Fighter X Tekken</tscIQ:answer></rdf:Description></rdf:li><rdf:li><rdf:Description tscIQ:orderId="2"><tscIQ:answer>Monster Hunter Frontier G</tscIQ:answer></rdf:Description></rdf:li><rdf:li><rdf:Description tscIQ:orderId="3"><tscIQ:answer>Viewtiful Joe 2: Secret of the Black Film</tscIQ:answer></rdf:Description></rdf:li></rdf:Seq></tscIQ:answerArray></rdf:Description></rdf:li><rdf:li><rdf:Description tscIQ:type="FITB" tscIQ:id="25"><tscIQ:question>What is the name of Patty's mother?</tscIQ:question><tscIQ:correctAnswer/><tscIQ:answerArray><rdf:Seq><rdf:li><rdf:Description tscIQ:orderId="0"><tscIQ:answer>Nina Lowell</tscIQ:answer></rdf:Description></rdf:li><rdf:li><rdf:Description tscIQ:orderId="1"><tscIQ:answer>Nina</tscIQ:answer></rdf:Description></rdf:li></rdf:Seq></tscIQ:answerArray></rdf:Description></rdf:li><rdf:li><rdf:Description tscIQ:type="MC" tscIQ:id="26"><tscIQ:question>What did Dante say to Trish when he assumed she died in Devil May Cry 1?</tscIQ:question><tscIQ:correctAnswer>2</tscIQ:correctAnswer><tscIQ:answerArray><rdf:Seq><rdf:li><rdf:Description tscIQ:orderId="0"><tscIQ:answer>You had my mother's face, but not her flame</tscIQ:answer></rdf:Description></rdf:li><rdf:li><rdf:Description tscIQ:orderId="1"><tscIQ:answer>I should have been the one to fill your dark soul with light</tscIQ:answer></rdf:Description></rdf:li><rdf:li><rdf:Description tscIQ:orderId="2"><tscIQ:answer>I can't lose you again</tscIQ:answer></rdf:Description></rdf:li><rdf:li><rdf:Description tscIQ:orderId="3"><tscIQ:answer>I should have been the one to save you from the darkness within</tscIQ:answer></rdf:Description></rdf:li></rdf:Seq></tscIQ:answerArray></rdf:Description></rdf:li><rdf:li><rdf:Description tscIQ:type="FITB" tscIQ:id="27"><tscIQ:question>What character was Dante originally supposed to be in development?</tscIQ:question><tscIQ:correctAnswer/><tscIQ:answerArray><rdf:Seq><rdf:li><rdf:Description tscIQ:orderId="0"><tscIQ:answer>leon kennedy</tscIQ:answer></rdf:Description></rdf:li><rdf:li><rdf:Description tscIQ:orderId="1"><tscIQ:answer>leon</tscIQ:answer></rdf:Description></rdf:li><rdf:li><rdf:Description tscIQ:orderId="2"><tscIQ:answer>leon s. kennedy</tscIQ:answer></rdf:Description></rdf:li><rdf:li><rdf:Description tscIQ:orderId="3"><tscIQ:answer>leon s kennedy</tscIQ:answer></rdf:Description></rdf:li></rdf:Seq></tscIQ:answerArray></rdf:Description></rdf:li><rdf:li><rdf:Description tscIQ:type="MC" tscIQ:id="28"><tscIQ:question>What is the name of the voice actor for Dante in Devil May Cry 2?</tscIQ:question><tscIQ:correctAnswer>2</tscIQ:correctAnswer><tscIQ:answerArray><rdf:Seq><rdf:li><rdf:Description tscIQ:orderId="0"><tscIQ:answer>Reuben Langdon</tscIQ:answer></rdf:Description></rdf:li><rdf:li><rdf:Description tscIQ:orderId="1"><tscIQ:answer>Matt Kaminsky</tscIQ:answer></rdf:Description></rdf:li><rdf:li><rdf:Description tscIQ:orderId="2"><tscIQ:answer>Drew Coombs</tscIQ:answer></rdf:Description></rdf:li></rdf:Seq></tscIQ:answerArray></rdf:Description></rdf:li><rdf:li><rdf:Description tscIQ:type="FITB" tscIQ:id="29"><tscIQ:question>What was Vergil's alias in the Devil May Cry prequel novel?</tscIQ:question><tscIQ:correctAnswer/><tscIQ:answerArray><rdf:Seq><rdf:li><rdf:Description tscIQ:orderId="0"><tscIQ:answer>Gilver</tscIQ:answer></rdf:Description></rdf:li></rdf:Seq></tscIQ:answerArray></rdf:Description></rdf:li><rdf:li><rdf:Description tscIQ:type="MC" tscIQ:id="30"><tscIQ:question>Lucia was meant to be playable in Devil May Cry 4: Special Edition but was cut due to time constraints</tscIQ:question><tscIQ:correctAnswer>2</tscIQ:correctAnswer><tscIQ:answerArray><rdf:Seq><rdf:li><rdf:Description tscIQ:orderId="0"><tscIQ:answer>True</tscIQ:answer></rdf:Description></rdf:li><rdf:li><rdf:Description tscIQ:orderId="1"><tscIQ:answer>False</tscIQ:answer></rdf:Description></rdf:li></rdf:Seq></tscIQ:answerArray></rdf:Description></rdf:li><rdf:li><rdf:Description tscIQ:type="MC" tscIQ:id="31"><tscIQ:question>What is the name of Nero's mechanical arms in Devil May Cry 5?</tscIQ:question><tscIQ:correctAnswer>2</tscIQ:correctAnswer><tscIQ:answerArray><rdf:Seq><rdf:li><rdf:Description tscIQ:orderId="0"><tscIQ:answer>Devil Bringer</tscIQ:answer></rdf:Description></rdf:li><rdf:li><rdf:Description tscIQ:orderId="1"><tscIQ:answer>Devil Breaker</tscIQ:answer></rdf:Description></rdf:li><rdf:li><rdf:Description tscIQ:orderId="2"><tscIQ:answer>Devil Killer</tscIQ:answer></rdf:Description></rdf:li><rdf:li><rdf:Description tscIQ:orderId="3"><tscIQ:answer>Hand of God</tscIQ:answer></rdf:Description></rdf:li></rdf:Seq></tscIQ:answerArray></rdf:Description></rdf:li><rdf:li><rdf:Description tscIQ:type="MC" tscIQ:id="32"><tscIQ:question>What is the first new weapon revealed for Dante in Devil May Cry 5?</tscIQ:question><tscIQ:correctAnswer>4</tscIQ:correctAnswer><tscIQ:answerArray><rdf:Seq><rdf:li><rdf:Description tscIQ:orderId="0"><tscIQ:answer>Lion Gauntlets</tscIQ:answer></rdf:Description></rdf:li><rdf:li><rdf:Description tscIQ:orderId="1"><tscIQ:answer>Mechanical Fists</tscIQ:answer></rdf:Description></rdf:li><rdf:li><rdf:Description tscIQ:orderId="2"><tscIQ:answer>Dual wielded motorcycle parts</tscIQ:answer></rdf:Description></rdf:li></rdf:Seq></tscIQ:answerArray></rdf:Description></rdf:li><rdf:li><rdf:Description tscIQ:type="MC" tscIQ:id="33"><tscIQ:question>What's the name of Nero's Devil May Cry 5 battle theme? </tscIQ:question><tscIQ:correctAnswer>1</tscIQ:correctAnswer><tscIQ:answerArray><rdf:Seq><rdf:li><rdf:Description tscIQ:orderId="0"><tscIQ:answer>Devil Trigger</tscIQ:answer></rdf:Description></rdf:li><rdf:li><rdf:Description tscIQ:orderId="1"><tscIQ:answer>Bang Bang Bang</tscIQ:answer></rdf:Description></rdf:li><rdf:li><rdf:Description tscIQ:orderId="2"><tscIQ:answer>Pull My Devil Trigger</tscIQ:answer></rdf:Description></rdf:li><rdf:li><rdf:Description tscIQ:orderId="3"><tscIQ:answer>Sons of Sparda</tscIQ:answer></rdf:Description></rdf:li></rdf:Seq></tscIQ:answerArray></rdf:Description></rdf:li><rdf:li><rdf:Description tscIQ:type="MC" tscIQ:id="34"><tscIQ:question>How many playable characters will Devil May Cry 5 have?</tscIQ:question><tscIQ:correctAnswer>4</tscIQ:correctAnswer><tscIQ:answerArray><rdf:Seq><rdf:li><rdf:Description tscIQ:orderId="0"><tscIQ:answer>2</tscIQ:answer></rdf:Description></rdf:li><rdf:li><rdf:Description tscIQ:orderId="1"><tscIQ:answer>1</tscIQ:answer></rdf:Description></rdf:li><rdf:li><rdf:Description tscIQ:orderId="2"><tscIQ:answer>3</tscIQ:answer></rdf:Description></rdf:li><rdf:li><rdf:Description tscIQ:orderId="3"><tscIQ:answer>3 in disc and 1 in DLC</tscIQ:answer></rdf:Description></rdf:li></rdf:Seq></tscIQ:answerArray></rdf:Description></rdf:li></rdf:Seq></tscIQ:questions></rdf:Description></rdf:li></rdf:Seq>
                     </xmpDM:markers>
                     <tscIQ:QuizParams><rdf:Bag><rdf:li xmpDM:name="txtPrev" xmpDM:value="&lt; Previous"/><rdf:li xmpDM:name="txtNext" xmpDM:value="Next &gt;"/><rdf:li xmpDM:name="txtAnswerQuestion" xmpDM:value="Let's Rock!"/><rdf:li xmpDM:name="txtSubmit" xmpDM:value="Submit"/><rdf:li xmpDM:name="txtReview" xmpDM:value="Replay Last Section"/><rdf:li xmpDM:name="txtReviewAnswer" xmpDM:value="View Answers"/><rdf:li xmpDM:name="txtContinue" xmpDM:value="Continue"/></rdf:Bag></tscIQ:QuizParams></rdf:Description>
               </rdf:li>
            </rdf:Bag>
         </xmpDM:Tracks>
         <tscDM:controller>
            <rdf:Description xmpDM:name="tscplayer">
               <tscDM:parameters>
                  <rdf:Bag>
                     <rdf:li xmpDM:name="autohide" xmpDM:value="true"/><rdf:li xmpDM:name="autoplay" xmpDM:value="false"/><rdf:li xmpDM:name="loop" xmpDM:value="false"/><rdf:li xmpDM:name="searchable" xmpDM:value="false"/><rdf:li xmpDM:name="captionsenabled" xmpDM:value="false"/><rdf:li xmpDM:name="sidebarenabled" xmpDM:value="false"/><rdf:li xmpDM:name="unicodeenabled" xmpDM:value="false"/><rdf:li xmpDM:name="backgroundcolor" xmpDM:value="000000"/><rdf:li xmpDM:name="sidebarlocation" xmpDM:value="left"/><rdf:li xmpDM:name="endaction" xmpDM:value="jumptourlnew"/><rdf:li xmpDM:name="endactionparam" xmpDM:value="https://originaldmc.github.io/DivinityStatue"/><rdf:li xmpDM:name="locale" xmpDM:value="en-US"/></rdf:Bag>
               </tscDM:parameters>
               <tscDM:controllerText>
                  <rdf:Bag>
                  </rdf:Bag>
               </tscDM:controllerText>
            </rdf:Description>
         </tscDM:controller>
         <tscDM:contentList>
            <rdf:Description>
               <tscDM:files>
                  <rdf:Seq>
                     <rdf:li xmpDM:name="0" xmpDM:value="OriginalDMCQuizV3.mp4"/><rdf:li xmpDM:name="1" xmpDM:value="OriginalDMCQuizV3_First_Frame.png"/></rdf:Seq>
               </tscDM:files>
            </rdf:Description>
         </tscDM:contentList>
      </rdf:Description>
   </rdf:RDF>
</x:xmpmeta>